crossbill/__init__.py
crossbill/bytes/__init__.py
crossbill/bytes/client.py
crossbill/bytes/pipeline_factory.py
crossbill/bytes/request.py
crossbill/bytes/request_codec.py
crossbill/bytes/response.py
crossbill/bytes/response_codec.py
crossbill/bytes/server.py
crossbill/client/__init__.py
crossbill/client/client.py
crossbill/core/__init__.py
crossbill/core/closable.py
crossbill/core/codec.py
crossbill/core/combined_filter.py
crossbill/core/filter.py
crossbill/core/filtered_service.py
crossbill/core/pipeline.py
crossbill/core/pipeline_factory.py
crossbill/core/reqrep.py
crossbill/core/request.py
crossbill/core/response.py
crossbill/core/service.py
crossbill/http/__init__.py
crossbill/http/client.py
crossbill/http/method.py
crossbill/http/pipeline_factory.py
crossbill/http/request.py
crossbill/http/request_codec.py
crossbill/http/response.py
crossbill/http/response_codec.py
crossbill/http/server.py
crossbill/http/service.py
crossbill/http/status.py
crossbill/server/__init__.py
crossbill/server/server.py
crossbill/string/__init__.py
crossbill/string/client.py
crossbill/string/pipeline_factory.py
crossbill/string/request.py
crossbill/string/request_codec.py
crossbill/string/response.py
crossbill/string/response_codec.py
crossbill/string/server.py
crossbill/string/service.py
crossbill/transport/__init__.py
crossbill/transport/address.py
crossbill/transport/bridge.py
crossbill-0.1.7.dist-info/licenses/LICENSE
crossbill-0.1.7.dist-info/METADATA
crossbill-0.1.7.dist-info/WHEEL
crossbill-0.1.7.dist-info/top_level.txt
crossbill-0.1.7.dist-info/RECORD
