Metadata-Version: 2.4
Name: crossbill
Version: 0.1.7
Summary: A library for building Finagle-style asynchronous clients and servers
Author-email: Ryan O'Neill <ryanoneill@gmail.com>
License-Expression: MIT
Project-URL: Repository, https://github.com/ryanoneill/crossbillpy
Keywords: crossbill,finagle,service,filter,asynchronous,future,request,response
Classifier: Development Status :: 2 - Pre-Alpha
Classifier: Framework :: AsyncIO
Classifier: Intended Audience :: Developers
Classifier: Programming Language :: Python :: 3
Classifier: Topic :: Communications
Classifier: Topic :: Internet
Classifier: Topic :: Software Development :: Libraries
Classifier: Topic :: System :: Networking
Classifier: Typing :: Typed
Requires-Python: >=3.11
License-File: LICENSE
Dynamic: license-file
